scope/__init__.py
scope/history_store.py
scope/memory_optimizer.py
scope/optimizer.py
scope/prompts.py
scope/strategic_store.py
scope/synthesizer.py
scope/utils.py
scope/models/__init__.py
scope/models/anthropic_adapter.py
scope/models/base.py
scope/models/litellm_adapter.py
scope/models/openai_adapter.py
scope_optimizer-0.1.1.dist-info/licenses/LICENSE
scope_optimizer-0.1.1.dist-info/METADATA
scope_optimizer-0.1.1.dist-info/WHEEL
scope_optimizer-0.1.1.dist-info/top_level.txt
scope_optimizer-0.1.1.dist-info/RECORD
