Metadata-Version: 2.4
Name: scope-optimizer
Version: 0.1.1
Summary: SCOPE: Self-evolving Context Optimization via Prompt Evolution - A framework for automatic prompt optimization
Author: SCOPE Team
License: MIT
Project-URL: Homepage, https://github.com/JarvisPei/SCOPE
Project-URL: Documentation, https://github.com/JarvisPei/SCOPE#readme
Project-URL: Repository, https://github.com/JarvisPei/SCOPE
Project-URL: Issues, https://github.com/JarvisPei/SCOPE/issues
Keywords: llm,prompt-optimization,agents,machine-learning,nlp,prompt-engineering
Classifier: Development Status :: 4 - Beta
Classifier: Intended Audience :: Developers
Classifier: Intended Audience :: Science/Research
Classifier: License :: OSI Approved :: MIT License
Classifier: Operating System :: OS Independent
Classifier: Programming Language :: Python :: 3
Classifier: Programming Language :: Python :: 3.8
Classifier: Programming Language :: Python :: 3.9
Classifier: Programming Language :: Python :: 3.10
Classifier: Programming Language :: Python :: 3.11
Classifier: Programming Language :: Python :: 3.12
Classifier: Topic :: Scientific/Engineering :: Artificial Intelligence
Requires-Python: >=3.8
License-File: LICENSE
Requires-Dist: openai>=1.0.0
Requires-Dist: anthropic>=0.18.0
Requires-Dist: litellm>=1.0.0
Requires-Dist: python-dotenv>=1.0.0
Provides-Extra: dev
Requires-Dist: pytest>=7.0.0; extra == "dev"
Requires-Dist: pytest-asyncio>=0.21.0; extra == "dev"
Requires-Dist: pytest-cov>=4.0.0; extra == "dev"
Requires-Dist: black>=23.0.0; extra == "dev"
Requires-Dist: ruff>=0.1.0; extra == "dev"
Requires-Dist: mypy>=1.0.0; extra == "dev"
Requires-Dist: pre-commit>=3.0.0; extra == "dev"
Dynamic: license-file
